tests/__init__.py
tests/test_activation_defaults.py
tests/test_audio.py
tests/test_classify_audio.py
tests/test_module.py
tests/test_ring_buffer.py
word_activation_recognition/__init__.py
word_activation_recognition/activation_defaults.py
word_activation_recognition/audio.py
word_activation_recognition/classify_audio.py
word_activation_recognition/ring_buffer.py
word_activation_recognition/word_recognition.py
word_activation_recognition/labels/star_trek_activation_phrase_v2.txt
word_activation_recognition/models/star_trek_activation_phrase_v2.tflite
word_activation_recognition-0.1.1.dist-info/LICENSE
word_activation_recognition-0.1.1.dist-info/METADATA
word_activation_recognition-0.1.1.dist-info/WHEEL
word_activation_recognition-0.1.1.dist-info/entry_points.txt
word_activation_recognition-0.1.1.dist-info/top_level.txt
word_activation_recognition-0.1.1.dist-info/RECORD
