Metadata-Version: 2.1
Name: word-activation-recognition
Version: 0.1.1
Summary: A library for audio keyword detection and processing with TensorFlow Lite models
Home-page: https://github.com/smartestmanuniverse/word_activation_recognition
Author: 0x07cb
Author-email: 83157348+0x07CB@users.noreply.github.com
License: MIT
Classifier: Programming Language :: Python :: 3
Classifier: License :: OSI Approved :: MIT License
Classifier: Operating System :: OS Independent
Requires-Python: >=3.11
License-File: LICENSE
Requires-Dist: librosa
Requires-Dist: numpy <2.0.0
Requires-Dist: pandas
Requires-Dist: pyaudio
Requires-Dist: sounddevice
Requires-Dist: soundfile
Requires-Dist: tflite-runtime
Requires-Dist: tflite-support
